{
  "designerVersion" : "1.11.52",
  "id" : "catpreparatorias",
  "name" : "catpreparatorias",
  "lastUpdate" : 1603153190350,
  "rows" : [
    [
      {
        "type" : "container",
        "dimension" : {
          "xs" : 12,
          "sm" : 12,
          "md" : 12,
          "lg" : 12
        },
        "propertyValues" : {
          "cssClasses" : {
            "type" : "constant",
            "value" : ""
          },
          "hidden" : {
            "type" : "constant",
            "value" : false
          },
          "repeatedCollection" : {
            "type" : "variable",
            "value" : ""
          }
        },
        "reference" : "4d2ca713-a6ba-47e2-86f4-9ac2342f538d",
        "hasValidationError" : false,
        "id" : "pbContainer",
        "rows" : [
          [
            {
              "type" : "container",
              "dimension" : {
                "xs" : 12,
                "sm" : 12,
                "md" : 12,
                "lg" : 12
              },
              "propertyValues" : {
                "cssClasses" : {
                  "type" : "constant",
                  "value" : ""
                },
                "hidden" : {
                  "type" : "constant",
                  "value" : false
                },
                "repeatedCollection" : {
                  "type" : "variable",
                  "value" : ""
                }
              },
              "reference" : "b96c552e-5778-45f8-8629-732598ac7e41",
              "hasValidationError" : false,
              "id" : "pbContainer",
              "rows" : [
                [
                  {
                    "type" : "component",
                    "dimension" : {
                      "xs" : 12,
                      "sm" : 12,
                      "md" : 2,
                      "lg" : 6
                    },
                    "propertyValues" : {
                      "cssClasses" : {
                        "type" : "constant",
                        "value" : ""
                      },
                      "hidden" : {
                        "type" : "constant",
                        "value" : false
                      },
                      "disabled" : {
                        "type" : "constant",
                        "value" : false
                      },
                      "label" : {
                        "type" : "interpolation",
                        "value" : "<i class=\" glyphicon glyphicon-arrow-left\" aria-hidden=\"true\"></i> Regresar"
                      },
                      "alignment" : {
                        "type" : "constant",
                        "value" : "left"
                      },
                      "buttonStyle" : {
                        "type" : "constant",
                        "value" : "dark"
                      },
                      "action" : {
                        "type" : "constant",
                        "value" : "Submit task"
                      },
                      "assign" : {
                        "type" : "constant",
                        "value" : false
                      },
                      "url" : {
                        "type" : "interpolation"
                      },
                      "responseStatusCode" : {
                        "type" : "variable",
                        "value" : ""
                      },
                      "dataToSend" : {
                        "type" : "constant"
                      },
                      "dataFromSuccess" : {
                        "type" : "variable",
                        "value" : ""
                      },
                      "closeOnSuccess" : {
                        "type" : "constant",
                        "value" : false
                      },
                      "dataFromError" : {
                        "type" : "variable",
                        "value" : ""
                      },
                      "targetUrlOnSuccess" : {
                        "type" : "interpolation"
                      },
                      "collectionToModify" : {
                        "type" : "variable"
                      },
                      "modalId" : {
                        "type" : "constant",
                        "value" : ""
                      },
                      "collectionPosition" : {
                        "type" : "constant",
                        "value" : "Last"
                      },
                      "valueToAdd" : {
                        "type" : "constant"
                      },
                      "removeItem" : {
                        "type" : "variable"
                      }
                    },
                    "reference" : "7e02476e-267b-45ad-b40f-d11ada2ea9ea",
                    "hasValidationError" : false,
                    "id" : "customWidgetButtoncustome"
                  },
                  {
                    "type" : "component",
                    "dimension" : {
                      "xs" : 12,
                      "sm" : 12,
                      "md" : 8,
                      "lg" : 6
                    },
                    "propertyValues" : {
                      "cssClasses" : {
                        "type" : "constant",
                        "value" : ""
                      },
                      "hidden" : {
                        "type" : "constant",
                        "value" : false
                      },
                      "text" : {
                        "type" : "interpolation",
                        "value" : "<b>Catalogo de Preparatorias y Bachillerato</b>"
                      },
                      "level" : {
                        "type" : "constant",
                        "value" : "Level 2"
                      },
                      "alignment" : {
                        "type" : "constant",
                        "value" : "center"
                      }
                    },
                    "reference" : "91d85ee2-8108-4371-a0ec-9bc149182921",
                    "hasValidationError" : false,
                    "id" : "pbTitle"
                  }
                ]
              ]
            }
          ],
          [
            {
              "type" : "component",
              "dimension" : {
                "xs" : 12,
                "sm" : 12,
                "md" : 12,
                "lg" : 12
              },
              "propertyValues" : {
                "cssClasses" : {
                  "type" : "constant",
                  "value" : "linia-separadora"
                },
                "hidden" : {
                  "type" : "constant",
                  "value" : false
                },
                "labelHidden" : {
                  "type" : "constant",
                  "value" : true
                },
                "label" : {
                  "type" : "interpolation",
                  "value" : "Default label"
                },
                "labelPosition" : {
                  "type" : "constant",
                  "value" : "top"
                },
                "labelWidth" : {
                  "type" : "constant",
                  "value" : 4
                },
                "allowHTML" : {
                  "type" : "constant",
                  "value" : true
                },
                "text" : {
                  "type" : "interpolation",
                  "value" : ""
                },
                "alignment" : {
                  "type" : "constant",
                  "value" : "left"
                }
              },
              "reference" : "34a5d2bc-9517-4052-bd8f-887c428acfd8",
              "hasValidationError" : false,
              "id" : "pbText"
            }
          ],
          [
            {
              "type" : "container",
              "dimension" : {
                "xs" : 12,
                "sm" : 12,
                "md" : 12,
                "lg" : 12
              },
              "propertyValues" : {
                "cssClasses" : {
                  "type" : "constant",
                  "value" : ""
                },
                "hidden" : {
                  "type" : "constant",
                  "value" : false
                },
                "repeatedCollection" : {
                  "type" : "variable",
                  "value" : ""
                }
              },
              "reference" : "d11949ab-967d-420f-b3e6-a80493a30834",
              "hasValidationError" : false,
              "id" : "pbContainer",
              "rows" : [
                [
                  {
                    "type" : "container",
                    "dimension" : {
                      "xs" : 12,
                      "sm" : 12,
                      "md" : 12,
                      "lg" : 12
                    },
                    "propertyValues" : {
                      "cssClasses" : {
                        "type" : "constant",
                        "value" : ""
                      },
                      "hidden" : {
                        "type" : "constant",
                        "value" : false
                      },
                      "repeatedCollection" : {
                        "type" : "variable",
                        "value" : ""
                      }
                    },
                    "reference" : "a22b0869-45c8-43c7-b924-3b7a08f5b2a3",
                    "hasValidationError" : false,
                    "id" : "pbContainer",
                    "rows" : [
                      [
                        {
                          "type" : "component",
                          "dimension" : {
                            "xs" : 12,
                            "sm" : 12,
                            "md" : 1,
                            "lg" : 3
                          },
                          "propertyValues" : {
                            "cssClasses" : {
                              "type" : "constant",
                              "value" : ""
                            },
                            "hidden" : {
                              "type" : "constant",
                              "value" : false
                            },
                            "disabled" : {
                              "type" : "constant",
                              "value" : false
                            },
                            "label" : {
                              "type" : "interpolation",
                              "value" : "filtro"
                            },
                            "alignment" : {
                              "type" : "constant",
                              "value" : "left"
                            },
                            "buttonStyle" : {
                              "type" : "constant",
                              "value" : "primary"
                            },
                            "action" : {
                              "type" : "constant",
                              "value" : "Open modal"
                            },
                            "assign" : {
                              "type" : "constant",
                              "value" : false
                            },
                            "url" : {
                              "type" : "interpolation"
                            },
                            "responseStatusCode" : {
                              "type" : "variable",
                              "value" : ""
                            },
                            "dataToSend" : {
                              "type" : "constant"
                            },
                            "dataFromSuccess" : {
                              "type" : "variable",
                              "value" : ""
                            },
                            "closeOnSuccess" : {
                              "type" : "constant",
                              "value" : false
                            },
                            "dataFromError" : {
                              "type" : "variable",
                              "value" : ""
                            },
                            "targetUrlOnSuccess" : {
                              "type" : "interpolation"
                            },
                            "collectionToModify" : {
                              "type" : "variable"
                            },
                            "modalId" : {
                              "type" : "constant",
                              "value" : "filtrado"
                            },
                            "collectionPosition" : {
                              "type" : "constant",
                              "value" : "Last"
                            },
                            "valueToAdd" : {
                              "type" : "constant"
                            },
                            "removeItem" : {
                              "type" : "variable"
                            }
                          },
                          "reference" : "0f5c01ab-ef95-4bc1-bb95-2366621cda09",
                          "hasValidationError" : false,
                          "id" : "pbButton"
                        },
                        {
                          "type" : "component",
                          "dimension" : {
                            "xs" : 12,
                            "sm" : 12,
                            "md" : 2,
                            "lg" : 3
                          },
                          "propertyValues" : {
                            "cssClasses" : {
                              "type" : "constant",
                              "value" : ""
                            },
                            "hidden" : {
                              "type" : "constant",
                              "value" : false
                            },
                            "disabled" : {
                              "type" : "constant",
                              "value" : false
                            },
                            "label" : {
                              "type" : "interpolation",
                              "value" : "Filtro específico"
                            },
                            "alignment" : {
                              "type" : "constant",
                              "value" : "left"
                            },
                            "buttonStyle" : {
                              "type" : "constant",
                              "value" : "primary"
                            },
                            "action" : {
                              "type" : "constant",
                              "value" : "Open modal"
                            },
                            "assign" : {
                              "type" : "constant",
                              "value" : false
                            },
                            "url" : {
                              "type" : "interpolation"
                            },
                            "responseStatusCode" : {
                              "type" : "variable",
                              "value" : ""
                            },
                            "dataToSend" : {
                              "type" : "constant"
                            },
                            "dataFromSuccess" : {
                              "type" : "variable",
                              "value" : ""
                            },
                            "closeOnSuccess" : {
                              "type" : "constant",
                              "value" : false
                            },
                            "dataFromError" : {
                              "type" : "variable",
                              "value" : ""
                            },
                            "targetUrlOnSuccess" : {
                              "type" : "interpolation"
                            },
                            "collectionToModify" : {
                              "type" : "variable"
                            },
                            "modalId" : {
                              "type" : "constant",
                              "value" : "filtroespecifico"
                            },
                            "collectionPosition" : {
                              "type" : "constant",
                              "value" : "Last"
                            },
                            "valueToAdd" : {
                              "type" : "constant"
                            },
                            "removeItem" : {
                              "type" : "variable"
                            }
                          },
                          "reference" : "b483e063-b974-41cb-adb9-757b8b9e2bae",
                          "hasValidationError" : false,
                          "id" : "pbButton"
                        },
                        {
                          "type" : "component",
                          "dimension" : {
                            "xs" : 12,
                            "sm" : 12,
                            "md" : 3,
                            "lg" : 3
                          },
                          "propertyValues" : {
                            "cssClasses" : {
                              "type" : "constant",
                              "value" : ""
                            },
                            "hidden" : {
                              "type" : "constant",
                              "value" : false
                            },
                            "disabled" : {
                              "type" : "constant",
                              "value" : false
                            },
                            "label" : {
                              "type" : "interpolation",
                              "value" : "<i class=\"glyphicon glyphicon-print\"></i> Imprimir"
                            },
                            "alignment" : {
                              "type" : "constant",
                              "value" : "center"
                            },
                            "buttonStyle" : {
                              "type" : "constant",
                              "value" : "warning"
                            },
                            "action" : {
                              "type" : "constant",
                              "value" : "Submit task"
                            },
                            "assign" : {
                              "type" : "constant",
                              "value" : false
                            },
                            "url" : {
                              "type" : "interpolation"
                            },
                            "responseStatusCode" : {
                              "type" : "variable",
                              "value" : ""
                            },
                            "dataToSend" : {
                              "type" : "constant"
                            },
                            "dataFromSuccess" : {
                              "type" : "variable",
                              "value" : ""
                            },
                            "closeOnSuccess" : {
                              "type" : "constant",
                              "value" : false
                            },
                            "dataFromError" : {
                              "type" : "variable",
                              "value" : ""
                            },
                            "targetUrlOnSuccess" : {
                              "type" : "interpolation"
                            },
                            "collectionToModify" : {
                              "type" : "variable"
                            },
                            "modalId" : {
                              "type" : "constant",
                              "value" : ""
                            },
                            "collectionPosition" : {
                              "type" : "constant",
                              "value" : "Last"
                            },
                            "valueToAdd" : {
                              "type" : "constant"
                            },
                            "removeItem" : {
                              "type" : "variable"
                            }
                          },
                          "reference" : "8af2e228-6c4a-470d-8221-21064407978a",
                          "hasValidationError" : false,
                          "id" : "customWidgetButtoncustome"
                        },
                        {
                          "type" : "container",
                          "dimension" : {
                            "xs" : 12,
                            "sm" : 12,
                            "md" : 6,
                            "lg" : 3
                          },
                          "propertyValues" : {
                            "cssClasses" : {
                              "type" : "constant",
                              "value" : ""
                            },
                            "hidden" : {
                              "type" : "constant",
                              "value" : false
                            },
                            "repeatedCollection" : {
                              "type" : "variable",
                              "value" : ""
                            }
                          },
                          "reference" : "45020a76-5a1a-46fd-b0cb-40493f691d25",
                          "hasValidationError" : false,
                          "id" : "pbContainer",
                          "rows" : [
                            [
                              {
                                "type" : "component",
                                "dimension" : {
                                  "xs" : 12,
                                  "sm" : 12,
                                  "md" : 6,
                                  "lg" : 4
                                },
                                "propertyValues" : {
                                  "cssClasses" : {
                                    "type" : "constant",
                                    "value" : ""
                                  },
                                  "hidden" : {
                                    "type" : "constant",
                                    "value" : false
                                  },
                                  "disabled" : {
                                    "type" : "constant",
                                    "value" : false
                                  },
                                  "label" : {
                                    "type" : "interpolation",
                                    "value" : "<i class=\"glyphicon glyphicon-plus\"></i> Agregar"
                                  },
                                  "alignment" : {
                                    "type" : "constant",
                                    "value" : "right"
                                  },
                                  "buttonStyle" : {
                                    "type" : "constant",
                                    "value" : "warning"
                                  },
                                  "action" : {
                                    "type" : "constant",
                                    "value" : "Submit task"
                                  },
                                  "assign" : {
                                    "type" : "constant",
                                    "value" : false
                                  },
                                  "url" : {
                                    "type" : "interpolation"
                                  },
                                  "responseStatusCode" : {
                                    "type" : "variable",
                                    "value" : ""
                                  },
                                  "dataToSend" : {
                                    "type" : "constant"
                                  },
                                  "dataFromSuccess" : {
                                    "type" : "variable",
                                    "value" : ""
                                  },
                                  "closeOnSuccess" : {
                                    "type" : "constant",
                                    "value" : false
                                  },
                                  "dataFromError" : {
                                    "type" : "variable",
                                    "value" : ""
                                  },
                                  "targetUrlOnSuccess" : {
                                    "type" : "interpolation"
                                  },
                                  "collectionToModify" : {
                                    "type" : "variable"
                                  },
                                  "modalId" : {
                                    "type" : "constant",
                                    "value" : ""
                                  },
                                  "collectionPosition" : {
                                    "type" : "constant",
                                    "value" : "Last"
                                  },
                                  "valueToAdd" : {
                                    "type" : "constant"
                                  },
                                  "removeItem" : {
                                    "type" : "variable"
                                  }
                                },
                                "reference" : "f9024b4b-f6bc-4ecf-a7b0-d0510c62e06a",
                                "hasValidationError" : false,
                                "id" : "customWidgetButtoncustome"
                              },
                              {
                                "type" : "component",
                                "dimension" : {
                                  "xs" : 12,
                                  "sm" : 12,
                                  "md" : 3,
                                  "lg" : 4
                                },
                                "propertyValues" : {
                                  "cssClasses" : {
                                    "type" : "constant",
                                    "value" : ""
                                  },
                                  "hidden" : {
                                    "type" : "constant",
                                    "value" : false
                                  },
                                  "disabled" : {
                                    "type" : "constant",
                                    "value" : false
                                  },
                                  "label" : {
                                    "type" : "interpolation",
                                    "value" : "<i class=\"glyphicon glyphicon-download-alt\"></i> Excel"
                                  },
                                  "alignment" : {
                                    "type" : "constant",
                                    "value" : "right"
                                  },
                                  "buttonStyle" : {
                                    "type" : "constant",
                                    "value" : "warning"
                                  },
                                  "action" : {
                                    "type" : "constant",
                                    "value" : "Submit task"
                                  },
                                  "assign" : {
                                    "type" : "constant",
                                    "value" : false
                                  },
                                  "url" : {
                                    "type" : "interpolation"
                                  },
                                  "responseStatusCode" : {
                                    "type" : "variable",
                                    "value" : ""
                                  },
                                  "dataToSend" : {
                                    "type" : "constant"
                                  },
                                  "dataFromSuccess" : {
                                    "type" : "variable",
                                    "value" : ""
                                  },
                                  "closeOnSuccess" : {
                                    "type" : "constant",
                                    "value" : false
                                  },
                                  "dataFromError" : {
                                    "type" : "variable",
                                    "value" : ""
                                  },
                                  "targetUrlOnSuccess" : {
                                    "type" : "interpolation"
                                  },
                                  "collectionToModify" : {
                                    "type" : "variable"
                                  },
                                  "modalId" : {
                                    "type" : "constant",
                                    "value" : ""
                                  },
                                  "collectionPosition" : {
                                    "type" : "constant",
                                    "value" : "Last"
                                  },
                                  "valueToAdd" : {
                                    "type" : "constant"
                                  },
                                  "removeItem" : {
                                    "type" : "variable"
                                  }
                                },
                                "reference" : "aae485ab-5f34-487c-a99f-e7e12403a8f1",
                                "hasValidationError" : false,
                                "id" : "customWidgetButtoncustome"
                              },
                              {
                                "type" : "component",
                                "dimension" : {
                                  "xs" : 12,
                                  "sm" : 12,
                                  "md" : 3,
                                  "lg" : 4
                                },
                                "propertyValues" : {
                                  "cssClasses" : {
                                    "type" : "constant",
                                    "value" : ""
                                  },
                                  "hidden" : {
                                    "type" : "constant",
                                    "value" : false
                                  },
                                  "disabled" : {
                                    "type" : "constant",
                                    "value" : false
                                  },
                                  "label" : {
                                    "type" : "interpolation",
                                    "value" : "<i class=\"glyphicon glyphicon-download-alt\"></i> PDF"
                                  },
                                  "alignment" : {
                                    "type" : "constant",
                                    "value" : "right"
                                  },
                                  "buttonStyle" : {
                                    "type" : "constant",
                                    "value" : "warning"
                                  },
                                  "action" : {
                                    "type" : "constant",
                                    "value" : "Submit task"
                                  },
                                  "assign" : {
                                    "type" : "constant",
                                    "value" : false
                                  },
                                  "url" : {
                                    "type" : "interpolation"
                                  },
                                  "responseStatusCode" : {
                                    "type" : "variable",
                                    "value" : ""
                                  },
                                  "dataToSend" : {
                                    "type" : "constant"
                                  },
                                  "dataFromSuccess" : {
                                    "type" : "variable",
                                    "value" : ""
                                  },
                                  "closeOnSuccess" : {
                                    "type" : "constant",
                                    "value" : false
                                  },
                                  "dataFromError" : {
                                    "type" : "variable",
                                    "value" : ""
                                  },
                                  "targetUrlOnSuccess" : {
                                    "type" : "interpolation"
                                  },
                                  "collectionToModify" : {
                                    "type" : "variable"
                                  },
                                  "modalId" : {
                                    "type" : "constant",
                                    "value" : ""
                                  },
                                  "collectionPosition" : {
                                    "type" : "constant",
                                    "value" : "Last"
                                  },
                                  "valueToAdd" : {
                                    "type" : "constant"
                                  },
                                  "removeItem" : {
                                    "type" : "variable"
                                  }
                                },
                                "reference" : "bfcf723c-2355-4316-9e61-9aff19a0f441",
                                "hasValidationError" : false,
                                "id" : "customWidgetButtoncustome"
                              }
                            ]
                          ]
                        }
                      ],
                      [
                        {
                          "type" : "component",
                          "dimension" : {
                            "xs" : 12,
                            "sm" : 12,
                            "md" : 3,
                            "lg" : 3
                          },
                          "propertyValues" : {
                            "cssClasses" : {
                              "type" : "constant",
                              "value" : ""
                            },
                            "hidden" : {
                              "type" : "constant",
                              "value" : false
                            },
                            "labelHidden" : {
                              "type" : "constant",
                              "value" : true
                            },
                            "label" : {
                              "type" : "interpolation",
                              "value" : "Default label"
                            },
                            "labelPosition" : {
                              "type" : "constant",
                              "value" : "top"
                            },
                            "labelWidth" : {
                              "type" : "constant",
                              "value" : 4
                            },
                            "allowHTML" : {
                              "type" : "constant",
                              "value" : true
                            },
                            "text" : {
                              "type" : "interpolation",
                              "value" : "Filtrado por: <b>nombre filtro</b>"
                            },
                            "alignment" : {
                              "type" : "constant",
                              "value" : "left"
                            }
                          },
                          "reference" : "30846e3a-8fde-41a6-8694-ad6db5e2c333",
                          "hasValidationError" : false,
                          "id" : "pbText"
                        },
                        {
                          "type" : "container",
                          "dimension" : {
                            "xs" : 12,
                            "sm" : 12,
                            "md" : 6,
                            "lg" : 3
                          },
                          "propertyValues" : {
                            "cssClasses" : {
                              "type" : "constant",
                              "value" : ""
                            },
                            "hidden" : {
                              "type" : "constant",
                              "value" : false
                            },
                            "repeatedCollection" : {
                              "type" : "variable",
                              "value" : ""
                            }
                          },
                          "reference" : "08443d20-f629-4e9e-97b5-67de8942d5c7",
                          "hasValidationError" : false,
                          "id" : "pbContainer",
                          "rows" : [
                            [
                              {
                                "type" : "component",
                                "dimension" : {
                                  "xs" : 12,
                                  "sm" : 12,
                                  "md" : 12,
                                  "lg" : 12
                                },
                                "propertyValues" : {
                                  "cssClasses" : {
                                    "type" : "constant",
                                    "value" : ""
                                  },
                                  "hidden" : {
                                    "type" : "constant",
                                    "value" : false
                                  },
                                  "labelHidden" : {
                                    "type" : "constant",
                                    "value" : true
                                  },
                                  "label" : {
                                    "type" : "interpolation",
                                    "value" : "Default label"
                                  },
                                  "labelPosition" : {
                                    "type" : "constant",
                                    "value" : "top"
                                  },
                                  "labelWidth" : {
                                    "type" : "constant",
                                    "value" : 4
                                  },
                                  "allowHTML" : {
                                    "type" : "constant",
                                    "value" : true
                                  },
                                  "text" : {
                                    "type" : "interpolation",
                                    "value" : "<br/>"
                                  },
                                  "alignment" : {
                                    "type" : "constant",
                                    "value" : "left"
                                  }
                                },
                                "reference" : "4dbd73e1-f996-4c77-8bdb-bb7be9f02820",
                                "hasValidationError" : false,
                                "id" : "pbText"
                              }
                            ],
                            [
                              {
                                "type" : "component",
                                "dimension" : {
                                  "xs" : 12,
                                  "sm" : 12,
                                  "md" : 6,
                                  "lg" : 6
                                },
                                "propertyValues" : {
                                  "cssClasses" : {
                                    "type" : "constant",
                                    "value" : ""
                                  },
                                  "hidden" : {
                                    "type" : "constant",
                                    "value" : false
                                  },
                                  "disabled" : {
                                    "type" : "constant",
                                    "value" : false
                                  },
                                  "label" : {
                                    "type" : "interpolation",
                                    "value" : "<i class=\"glyphicon glyphicon-time\"></i> Asignar hora"
                                  },
                                  "alignment" : {
                                    "type" : "constant",
                                    "value" : "right"
                                  },
                                  "buttonStyle" : {
                                    "type" : "constant",
                                    "value" : "dark"
                                  },
                                  "action" : {
                                    "type" : "constant",
                                    "value" : "Submit task"
                                  },
                                  "assign" : {
                                    "type" : "constant",
                                    "value" : false
                                  },
                                  "url" : {
                                    "type" : "interpolation"
                                  },
                                  "responseStatusCode" : {
                                    "type" : "variable",
                                    "value" : ""
                                  },
                                  "dataToSend" : {
                                    "type" : "constant"
                                  },
                                  "dataFromSuccess" : {
                                    "type" : "variable",
                                    "value" : ""
                                  },
                                  "closeOnSuccess" : {
                                    "type" : "constant",
                                    "value" : false
                                  },
                                  "dataFromError" : {
                                    "type" : "variable",
                                    "value" : ""
                                  },
                                  "targetUrlOnSuccess" : {
                                    "type" : "interpolation"
                                  },
                                  "collectionToModify" : {
                                    "type" : "variable"
                                  },
                                  "modalId" : {
                                    "type" : "constant",
                                    "value" : ""
                                  },
                                  "collectionPosition" : {
                                    "type" : "constant",
                                    "value" : "Last"
                                  },
                                  "valueToAdd" : {
                                    "type" : "constant"
                                  },
                                  "removeItem" : {
                                    "type" : "variable"
                                  }
                                },
                                "reference" : "d61818b2-6e5a-44bb-b9df-83d8c3c84836",
                                "hasValidationError" : false,
                                "id" : "customWidgetButtoncustome"
                              },
                              {
                                "type" : "component",
                                "dimension" : {
                                  "xs" : 12,
                                  "sm" : 12,
                                  "md" : 6,
                                  "lg" : 6
                                },
                                "propertyValues" : {
                                  "cssClasses" : {
                                    "type" : "constant",
                                    "value" : ""
                                  },
                                  "hidden" : {
                                    "type" : "constant",
                                    "value" : false
                                  },
                                  "disabled" : {
                                    "type" : "constant",
                                    "value" : false
                                  },
                                  "label" : {
                                    "type" : "interpolation",
                                    "value" : "<i class=\"glyphicon glyphicon-refresh\"></i> Sincronizar"
                                  },
                                  "alignment" : {
                                    "type" : "constant",
                                    "value" : "left"
                                  },
                                  "buttonStyle" : {
                                    "type" : "constant",
                                    "value" : "warning"
                                  },
                                  "action" : {
                                    "type" : "constant",
                                    "value" : "Submit task"
                                  },
                                  "assign" : {
                                    "type" : "constant",
                                    "value" : false
                                  },
                                  "url" : {
                                    "type" : "interpolation"
                                  },
                                  "responseStatusCode" : {
                                    "type" : "variable",
                                    "value" : ""
                                  },
                                  "dataToSend" : {
                                    "type" : "constant"
                                  },
                                  "dataFromSuccess" : {
                                    "type" : "variable",
                                    "value" : ""
                                  },
                                  "closeOnSuccess" : {
                                    "type" : "constant",
                                    "value" : false
                                  },
                                  "dataFromError" : {
                                    "type" : "variable",
                                    "value" : ""
                                  },
                                  "targetUrlOnSuccess" : {
                                    "type" : "interpolation"
                                  },
                                  "collectionToModify" : {
                                    "type" : "variable"
                                  },
                                  "modalId" : {
                                    "type" : "constant",
                                    "value" : ""
                                  },
                                  "collectionPosition" : {
                                    "type" : "constant",
                                    "value" : "Last"
                                  },
                                  "valueToAdd" : {
                                    "type" : "constant"
                                  },
                                  "removeItem" : {
                                    "type" : "variable"
                                  }
                                },
                                "reference" : "c450bb89-48b6-4c30-b895-9e6d77d65f1e",
                                "hasValidationError" : false,
                                "id" : "customWidgetButtoncustome"
                              }
                            ]
                          ]
                        }
                      ]
                    ]
                  }
                ],
                [
                  {
                    "type" : "component",
                    "dimension" : {
                      "xs" : 12,
                      "sm" : 12,
                      "md" : 12,
                      "lg" : 12
                    },
                    "propertyValues" : {
                      "cssClasses" : {
                        "type" : "constant",
                        "value" : ""
                      },
                      "hidden" : {
                        "type" : "constant",
                        "value" : false
                      },
                      "allowHTML" : {
                        "type" : "constant",
                        "value" : true
                      },
                      "headers" : {
                        "type" : "constant",
                        "value" : [
                          "No. BPM",
                          "No.Banner",
                          "Descripción",
                          "Pais",
                          "Ciudad/Estado",
                          "usuario de creacíon",
                          "Fecha de creacion",
                          "Fecha de importación",
                          "Convenio P. Examen",
                          "Pase directo",
                          "Acciones"
                        ]
                      },
                      "content" : {
                        "type" : "constant"
                      },
                      "columnsKey" : {
                        "type" : "constant"
                      },
                      "selectedRow" : {
                        "type" : "variable",
                        "value" : ""
                      },
                      "striped" : {
                        "type" : "constant",
                        "value" : true
                      },
                      "condensed" : {
                        "type" : "constant",
                        "value" : false
                      },
                      "bordered" : {
                        "type" : "constant",
                        "value" : false
                      }
                    },
                    "reference" : "e02417ab-e43c-4b5c-88dc-bfba2b563106",
                    "hasValidationError" : false,
                    "id" : "pbTable"
                  }
                ]
              ]
            }
          ]
        ]
      }
    ],
    [
      {
        "type" : "modalContainer",
        "dimension" : {
          "xs" : 12,
          "sm" : 12,
          "md" : 12,
          "lg" : 12
        },
        "propertyValues" : {
          "cssClasses" : {
            "type" : "constant",
            "value" : ""
          },
          "modalId" : {
            "type" : "constant",
            "value" : "filtroespecifico"
          },
          "size" : {
            "type" : "constant",
            "value" : "lg"
          },
          "animation" : {
            "type" : "constant",
            "value" : true
          }
        },
        "reference" : "63f77666-b744-465d-8714-51a63e38767a",
        "hasValidationError" : false,
        "id" : "pbModalContainer",
        "container" : {
          "type" : "container",
          "dimension" : {
            "xs" : 12
          },
          "propertyValues" : { },
          "reference" : "ef9ded4f-235c-4555-b1cd-e9087a155c34",
          "hasValidationError" : false,
          "id" : "pbContainer",
          "rows" : [
            [
              {
                "type" : "component",
                "dimension" : {
                  "xs" : 12,
                  "sm" : 12,
                  "md" : 12,
                  "lg" : 12
                },
                "propertyValues" : {
                  "cssClasses" : {
                    "type" : "constant",
                    "value" : ""
                  },
                  "hidden" : {
                    "type" : "constant",
                    "value" : false
                  },
                  "text" : {
                    "type" : "interpolation",
                    "value" : "<b>Descripción del Filtro</b>"
                  },
                  "level" : {
                    "type" : "constant",
                    "value" : "Level 2"
                  },
                  "alignment" : {
                    "type" : "constant",
                    "value" : "center"
                  }
                },
                "reference" : "b48fa718-4f3f-4f1d-9865-09c47982f03e",
                "hasValidationError" : false,
                "id" : "pbTitle"
              }
            ],
            [
              {
                "type" : "component",
                "dimension" : {
                  "xs" : 12,
                  "sm" : 12,
                  "md" : 4,
                  "lg" : 4
                },
                "propertyValues" : {
                  "cssClasses" : {
                    "type" : "constant",
                    "value" : ""
                  },
                  "hidden" : {
                    "type" : "constant",
                    "value" : false
                  },
                  "disabled" : {
                    "type" : "constant",
                    "value" : false
                  },
                  "required" : {
                    "type" : "constant",
                    "value" : false
                  },
                  "labelHidden" : {
                    "type" : "constant",
                    "value" : false
                  },
                  "label" : {
                    "type" : "interpolation",
                    "value" : "Columna"
                  },
                  "labelPosition" : {
                    "type" : "constant",
                    "value" : "top"
                  },
                  "labelWidth" : {
                    "type" : "constant",
                    "value" : 4
                  },
                  "placeholder" : {
                    "type" : "interpolation",
                    "value" : "Seleccione la opción de filtrado"
                  },
                  "availableValues" : {
                    "type" : "constant"
                  },
                  "displayedKey" : {
                    "type" : "constant"
                  },
                  "returnedKey" : {
                    "type" : "constant"
                  },
                  "value" : {
                    "type" : "variable",
                    "value" : ""
                  }
                },
                "reference" : "9190860d-4cba-45b5-b5f3-c3821f043557",
                "hasValidationError" : false,
                "id" : "pbSelect"
              },
              {
                "type" : "component",
                "dimension" : {
                  "xs" : 12,
                  "sm" : 12,
                  "md" : 4,
                  "lg" : 4
                },
                "propertyValues" : {
                  "cssClasses" : {
                    "type" : "constant",
                    "value" : ""
                  },
                  "hidden" : {
                    "type" : "constant",
                    "value" : false
                  },
                  "disabled" : {
                    "type" : "constant",
                    "value" : false
                  },
                  "required" : {
                    "type" : "constant",
                    "value" : false
                  },
                  "labelHidden" : {
                    "type" : "constant",
                    "value" : false
                  },
                  "label" : {
                    "type" : "interpolation",
                    "value" : "Operador"
                  },
                  "labelPosition" : {
                    "type" : "constant",
                    "value" : "top"
                  },
                  "labelWidth" : {
                    "type" : "constant",
                    "value" : 4
                  },
                  "placeholder" : {
                    "type" : "interpolation",
                    "value" : "Igual a"
                  },
                  "availableValues" : {
                    "type" : "constant"
                  },
                  "displayedKey" : {
                    "type" : "constant"
                  },
                  "returnedKey" : {
                    "type" : "constant"
                  },
                  "value" : {
                    "type" : "variable",
                    "value" : ""
                  }
                },
                "reference" : "b6330f8c-8f32-49e3-8df4-46ea9d6c8e43",
                "hasValidationError" : false,
                "id" : "pbSelect"
              },
              {
                "type" : "component",
                "dimension" : {
                  "xs" : 12,
                  "sm" : 12,
                  "md" : 4,
                  "lg" : 4
                },
                "propertyValues" : {
                  "cssClasses" : {
                    "type" : "constant",
                    "value" : ""
                  },
                  "hidden" : {
                    "type" : "constant",
                    "value" : false
                  },
                  "required" : {
                    "type" : "constant",
                    "value" : false
                  },
                  "minLength" : {
                    "type" : "constant",
                    "value" : ""
                  },
                  "maxLength" : {
                    "type" : "constant",
                    "value" : ""
                  },
                  "readOnly" : {
                    "type" : "constant",
                    "value" : false
                  },
                  "labelHidden" : {
                    "type" : "constant",
                    "value" : false
                  },
                  "label" : {
                    "type" : "interpolation",
                    "value" : "Valores"
                  },
                  "labelPosition" : {
                    "type" : "constant",
                    "value" : "top"
                  },
                  "labelWidth" : {
                    "type" : "constant",
                    "value" : 4
                  },
                  "placeholder" : {
                    "type" : "interpolation"
                  },
                  "value" : {
                    "type" : "variable",
                    "value" : ""
                  },
                  "type" : {
                    "type" : "constant",
                    "value" : "text"
                  },
                  "min" : {
                    "type" : "constant"
                  },
                  "max" : {
                    "type" : "constant"
                  },
                  "step" : {
                    "type" : "constant",
                    "value" : 1
                  }
                },
                "reference" : "84b215ba-c72a-41dd-9f1e-62891fad9ca1",
                "hasValidationError" : false,
                "id" : "pbInput"
              }
            ],
            [
              {
                "type" : "component",
                "dimension" : {
                  "xs" : 12,
                  "sm" : 12,
                  "md" : 12,
                  "lg" : 12
                },
                "propertyValues" : {
                  "cssClasses" : {
                    "type" : "constant",
                    "value" : ""
                  },
                  "hidden" : {
                    "type" : "constant",
                    "value" : false
                  },
                  "allowHTML" : {
                    "type" : "constant",
                    "value" : true
                  },
                  "headers" : {
                    "type" : "constant",
                    "value" : [
                      "Columna",
                      "Operador",
                      "Valor",
                      "X"
                    ]
                  },
                  "content" : {
                    "type" : "constant"
                  },
                  "columnsKey" : {
                    "type" : "constant"
                  },
                  "selectedRow" : {
                    "type" : "variable",
                    "value" : ""
                  },
                  "striped" : {
                    "type" : "constant",
                    "value" : true
                  },
                  "condensed" : {
                    "type" : "constant",
                    "value" : false
                  },
                  "bordered" : {
                    "type" : "constant",
                    "value" : false
                  }
                },
                "reference" : "1cc106a2-acfb-4cfc-bd5e-695d1577acac",
                "hasValidationError" : false,
                "id" : "pbTable"
              }
            ]
          ]
        }
      }
    ],
    [
      {
        "type" : "modalContainer",
        "dimension" : {
          "xs" : 12,
          "sm" : 12,
          "md" : 12,
          "lg" : 12
        },
        "propertyValues" : {
          "cssClasses" : {
            "type" : "constant",
            "value" : ""
          },
          "modalId" : {
            "type" : "constant",
            "value" : "filtrado"
          },
          "size" : {
            "type" : "constant",
            "value" : ""
          },
          "animation" : {
            "type" : "constant",
            "value" : true
          }
        },
        "reference" : "e873ff1f-2a28-4249-861d-2299010ba631",
        "hasValidationError" : false,
        "id" : "pbModalContainer",
        "container" : {
          "type" : "container",
          "dimension" : {
            "xs" : 12
          },
          "propertyValues" : { },
          "reference" : "6b69b309-53e6-46ce-9769-70e83adb4789",
          "hasValidationError" : false,
          "id" : "pbContainer",
          "rows" : [
            [
              {
                "type" : "component",
                "dimension" : {
                  "xs" : 12,
                  "sm" : 12,
                  "md" : 12,
                  "lg" : 12
                },
                "propertyValues" : {
                  "cssClasses" : {
                    "type" : "constant",
                    "value" : ""
                  },
                  "hidden" : {
                    "type" : "constant",
                    "value" : false
                  },
                  "readOnly" : {
                    "type" : "constant",
                    "value" : false
                  },
                  "required" : {
                    "type" : "constant",
                    "value" : false
                  },
                  "labelHidden" : {
                    "type" : "constant",
                    "value" : true
                  },
                  "label" : {
                    "type" : "interpolation",
                    "value" : "Default name"
                  },
                  "labelPosition" : {
                    "type" : "constant",
                    "value" : "top"
                  },
                  "labelWidth" : {
                    "type" : "constant",
                    "value" : 4
                  },
                  "placeholder" : {
                    "type" : "interpolation",
                    "value" : "nombre de la Preparatoria o bachillerato"
                  },
                  "availableValues" : {
                    "type" : "constant",
                    "value" : [
                      "Prepa Anahuac Puebla",
                      "Prepa Anahuac San luis",
                      "Prepa Anahuac Culiacan"
                    ]
                  },
                  "displayedKey" : {
                    "type" : "constant"
                  },
                  "value" : {
                    "type" : "variable",
                    "value" : ""
                  }
                },
                "reference" : "1edc88f8-f15e-46b8-a402-73ee3e1d550d",
                "hasValidationError" : false,
                "id" : "pbAutocomplete"
              }
            ],
            [
              {
                "type" : "component",
                "dimension" : {
                  "xs" : 12,
                  "sm" : 12,
                  "md" : 12,
                  "lg" : 12
                },
                "propertyValues" : {
                  "cssClasses" : {
                    "type" : "constant",
                    "value" : ""
                  },
                  "hidden" : {
                    "type" : "constant",
                    "value" : false
                  },
                  "disabled" : {
                    "type" : "constant",
                    "value" : false
                  },
                  "inline" : {
                    "type" : "constant",
                    "value" : false
                  },
                  "labelHidden" : {
                    "type" : "constant",
                    "value" : true
                  },
                  "label" : {
                    "type" : "interpolation",
                    "value" : ""
                  },
                  "labelPosition" : {
                    "type" : "constant",
                    "value" : "top"
                  },
                  "labelWidth" : {
                    "type" : "constant",
                    "value" : 4
                  },
                  "availableValues" : {
                    "type" : "constant",
                    "value" : [
                      "Todos",
                      "Prepa Anahuac Puebla",
                      "Prepa Anahuac San luis",
                      "Prepa Anahuac Culiacan"
                    ]
                  },
                  "displayedKey" : {
                    "type" : "constant"
                  },
                  "returnedKey" : {
                    "type" : "constant"
                  },
                  "selectedValues" : {
                    "type" : "variable",
                    "value" : ""
                  }
                },
                "reference" : "2296aaa7-e75d-40bf-8194-a9addbe2b2da",
                "hasValidationError" : false,
                "id" : "pbChecklist"
              }
            ],
            [
              {
                "type" : "container",
                "dimension" : {
                  "xs" : 12,
                  "sm" : 12,
                  "md" : 12,
                  "lg" : 12
                },
                "propertyValues" : {
                  "cssClasses" : {
                    "type" : "constant",
                    "value" : ""
                  },
                  "hidden" : {
                    "type" : "constant",
                    "value" : false
                  },
                  "repeatedCollection" : {
                    "type" : "variable",
                    "value" : ""
                  }
                },
                "reference" : "77d485ff-7655-491d-a155-4718a9f2b311",
                "hasValidationError" : false,
                "id" : "pbContainer",
                "rows" : [
                  [
                    {
                      "type" : "container",
                      "dimension" : {
                        "xs" : 12,
                        "sm" : 12,
                        "md" : 8,
                        "lg" : 4
                      },
                      "propertyValues" : {
                        "cssClasses" : {
                          "type" : "constant",
                          "value" : ""
                        },
                        "hidden" : {
                          "type" : "constant",
                          "value" : false
                        },
                        "repeatedCollection" : {
                          "type" : "variable",
                          "value" : ""
                        }
                      },
                      "reference" : "b6944571-4be1-41e8-930b-33d1972563d4",
                      "hasValidationError" : false,
                      "id" : "pbContainer",
                      "rows" : [
                        [ ]
                      ]
                    },
                    {
                      "type" : "component",
                      "dimension" : {
                        "xs" : 12,
                        "sm" : 12,
                        "md" : 2,
                        "lg" : 4
                      },
                      "propertyValues" : {
                        "cssClasses" : {
                          "type" : "constant",
                          "value" : ""
                        },
                        "hidden" : {
                          "type" : "constant",
                          "value" : false
                        },
                        "disabled" : {
                          "type" : "constant",
                          "value" : false
                        },
                        "label" : {
                          "type" : "interpolation",
                          "value" : "<i class=\"glyphicon glyphicon-trash\"></i> Limpiar"
                        },
                        "alignment" : {
                          "type" : "constant",
                          "value" : "center"
                        },
                        "buttonStyle" : {
                          "type" : "constant",
                          "value" : "dark"
                        },
                        "action" : {
                          "type" : "constant",
                          "value" : "Submit task"
                        },
                        "assign" : {
                          "type" : "constant",
                          "value" : false
                        },
                        "url" : {
                          "type" : "interpolation"
                        },
                        "responseStatusCode" : {
                          "type" : "variable",
                          "value" : ""
                        },
                        "dataToSend" : {
                          "type" : "constant"
                        },
                        "dataFromSuccess" : {
                          "type" : "variable",
                          "value" : ""
                        },
                        "closeOnSuccess" : {
                          "type" : "constant",
                          "value" : false
                        },
                        "dataFromError" : {
                          "type" : "variable",
                          "value" : ""
                        },
                        "targetUrlOnSuccess" : {
                          "type" : "interpolation"
                        },
                        "collectionToModify" : {
                          "type" : "variable"
                        },
                        "modalId" : {
                          "type" : "constant",
                          "value" : ""
                        },
                        "collectionPosition" : {
                          "type" : "constant",
                          "value" : "Last"
                        },
                        "valueToAdd" : {
                          "type" : "constant"
                        },
                        "removeItem" : {
                          "type" : "variable"
                        }
                      },
                      "reference" : "e91b0039-a77a-4327-9bc5-4684b92603a3",
                      "hasValidationError" : false,
                      "id" : "customWidgetButtoncustome"
                    },
                    {
                      "type" : "component",
                      "dimension" : {
                        "xs" : 12,
                        "sm" : 12,
                        "md" : 2,
                        "lg" : 4
                      },
                      "propertyValues" : {
                        "cssClasses" : {
                          "type" : "constant",
                          "value" : ""
                        },
                        "hidden" : {
                          "type" : "constant",
                          "value" : false
                        },
                        "disabled" : {
                          "type" : "constant",
                          "value" : false
                        },
                        "label" : {
                          "type" : "interpolation",
                          "value" : "<i class=\"glyphicon glyphicon-filter\"></i> Filtrar"
                        },
                        "alignment" : {
                          "type" : "constant",
                          "value" : "center"
                        },
                        "buttonStyle" : {
                          "type" : "constant",
                          "value" : "warning"
                        },
                        "action" : {
                          "type" : "constant",
                          "value" : "Submit task"
                        },
                        "assign" : {
                          "type" : "constant",
                          "value" : false
                        },
                        "url" : {
                          "type" : "interpolation"
                        },
                        "responseStatusCode" : {
                          "type" : "variable",
                          "value" : ""
                        },
                        "dataToSend" : {
                          "type" : "constant"
                        },
                        "dataFromSuccess" : {
                          "type" : "variable",
                          "value" : ""
                        },
                        "closeOnSuccess" : {
                          "type" : "constant",
                          "value" : false
                        },
                        "dataFromError" : {
                          "type" : "variable",
                          "value" : ""
                        },
                        "targetUrlOnSuccess" : {
                          "type" : "interpolation"
                        },
                        "collectionToModify" : {
                          "type" : "variable"
                        },
                        "modalId" : {
                          "type" : "constant",
                          "value" : ""
                        },
                        "collectionPosition" : {
                          "type" : "constant",
                          "value" : "Last"
                        },
                        "valueToAdd" : {
                          "type" : "constant"
                        },
                        "removeItem" : {
                          "type" : "variable"
                        }
                      },
                      "reference" : "80a7fff0-ab8a-4b30-a01c-dce0acc12b29",
                      "hasValidationError" : false,
                      "id" : "customWidgetButtoncustome"
                    }
                  ]
                ]
              }
            ]
          ]
        }
      }
    ]
  ],
  "assets" : [
    {
      "id" : "bbc69a80-dd1f-4f48-8676-a62f0340220e",
      "name" : "localization.json",
      "type" : "json",
      "order" : 0,
      "external" : false
    },
    {
      "id" : "fcd67248-8dc0-48d5-8f4f-ae1d6f737e72",
      "name" : "catpreparatoria.css",
      "type" : "css",
      "order" : 1,
      "external" : false
    },
    {
      "id" : "31010949-95d5-4bdc-8a58-6e063d1ff5f2",
      "name" : "style.css",
      "type" : "css",
      "order" : 0,
      "external" : false
    }
  ],
  "inactiveAssets" : [ ],
  "variables" : { },
  "hasValidationError" : false,
  "uuid" : "0c96fa15-1325-469f-9546-5ca8a36c5995",
  "type" : "page",
  "description" : "Page generated with Bonita UI designer"
}